localgraph/__init__.py
localgraph/utils.py
localgraph/evaluation/__init__.py
localgraph/evaluation/eval.py
localgraph/examples/__init__.py
localgraph/examples/simple_example.py
localgraph/pfs/__init__.py
localgraph/pfs/helpers.py
localgraph/pfs/main.py
localgraph/plotting/__init__.py
localgraph/plotting/helpers.py
localgraph/plotting/plot_graph.py
localgraph-0.1.2.dist-info/licenses/LICENSE
localgraph-0.1.2.dist-info/METADATA
localgraph-0.1.2.dist-info/WHEEL
localgraph-0.1.2.dist-info/top_level.txt
localgraph-0.1.2.dist-info/RECORD
