Metadata-Version: 2.4
Name: localgraph
Version: 0.1.2
Summary: Local graph estimation with pathwise feature selection
Author: Omar Melikechi
Author-email: omar.melikechi@gmail.com
Classifier: Programming Language :: Python :: 3
Classifier: License :: OSI Approved :: MIT License
Classifier: Operating System :: OS Independent
Requires-Python: >=3.6
License-File: LICENSE
Requires-Dist: ipss>=1.1.1
Requires-Dist: matplotlib>=3.0.0
Requires-Dist: networkx>=2.0
Requires-Dist: numpy>=1.16.0
Dynamic: author
Dynamic: author-email
Dynamic: classifier
Dynamic: description
Dynamic: description-content-type
Dynamic: license-file
Dynamic: requires-dist
Dynamic: requires-python
Dynamic: summary
